<?xml version="1.0" encoding="utf-8" ?><dwsync><file name="blackboard.jpg" server="shanegermann.com//montanameat/" local="3450477903" remote="318763443843399612" Dst="-1" /><file name="grassback.bmp" server="shanegermann.com//montanameat/" local="3450476624" remote="318763443843398652" Dst="-1" /><file name="masthead.png" server="shanegermann.com//montanameat/" local="3450483522" remote="318763443843405192" Dst="-1" /><file name="logo.png" server="shanegermann.com//montanameat/" local="3457878413" remote="318763443850774932" Dst="-1" /><file name="menuback.png" server="shanegermann.com//montanameat/" local="3450546707" remote="318763443843468372" Dst="-1" /><file name="menutag.png" server="shanegermann.com//montanameat/" local="3450548006" remote="318763443843469692" Dst="-1" /><file name="icon-beef.png" server="shanegermann.com//montanameat/" local="3451059259" remote="318763443843981552" Dst="-1" /><file name="icon-lamb.png" server="shanegermann.com//montanameat/" local="3451059743" remote="318763443843981552" Dst="-1" /><file name="icon-pig.png" server="shanegermann.com//montanameat/" local="3451057455" remote="318763443843981552" Dst="-1" /><file name="butcherpaper.png" server="shanegermann.com//montanameat/" local="3457960821" remote="318763443850857312" Dst="-1" /><file name="slideBurger.jpg" server="shanegermann.com//montanameat/" local="3451080313" remote="318763443844277772" Dst="-1" /><file name="slideCustard.jpg" server="shanegermann.com//montanameat/" local="3451080121" remote="318763443844277772" Dst="-1" /><file name="slideRib.jpg" server="shanegermann.com//montanameat/" local="3451080241" remote="318763443844277772" Dst="-1" /><file name="tileback.jpg" server="shanegermann.com//montanameat/" local="3453140676" remote="318763443846062532" Dst="-1" /><file name="chalkback.jpg" server="shanegermann.com//montanameat/" local="3457693728" remote="318763443850590252" Dst="-1" /><file name="butcherpaperTOP.png" server="shanegermann.com//montanameat/" local="3457873550" remote="318763443850770132" Dst="-1" /><file name="butcherpaperBOTTOM.png" server="shanegermann.com//montanameat/" local="3457874628" remote="318763443850771092" Dst="-1" /><file name="grass.png" server="shanegermann.com//montanameat/" local="3455901218" remote="318763443848824152" Dst="-1" /><file name="facebookicon.png" server="shanegermann.com//montanameat/" local="3457959331" remote="318763443850855812" Dst="-1" /></dwsync>