<?xml version="1.0" encoding="utf-8" ?><dwsync><file name="admin.php" server="shanegermann.com//montanameat/" local="3458210422" remote="318763443846142632" Dst="-1" /><file name="ajax-actions.php" server="shanegermann.com//montanameat/" local="3458210422" remote="318763443846142632" Dst="-1" /><file name="bookmark.php" server="shanegermann.com//montanameat/" local="3458210422" remote="318763443846142632" Dst="-1" /><file name="class-ftp-pure.php" server="shanegermann.com//montanameat/" local="3458210422" remote="318763443846142632" Dst="-1" /><file name="class-ftp-sockets.php" server="shanegermann.com//montanameat/" local="3458210422" remote="318763443846142632" Dst="-1" /><file name="class-ftp.php" server="shanegermann.com//montanameat/" local="3458210423" remote="318763443846142632" Dst="-1" /><file name="class-wp-comments-list-table.php" server="shanegermann.com//montanameat/" local="3458210423" remote="318763443846142632" Dst="-1" /><file name="class-wp-filesystem-base.php" server="shanegermann.com//montanameat/" local="3458210423" remote="318763443846142632" Dst="-1" /><file name="class-pclzip.php" server="shanegermann.com//montanameat/" local="3458210423" remote="318763443846142632" Dst="-1" /><file name="class-wp-filesystem-direct.php" server="shanegermann.com//montanameat/" local="3458210423" remote="318763443846142632" Dst="-1" /><file name="class-wp-filesystem-ftpext.php" server="shanegermann.com//montanameat/" local="3458210423" remote="318763443846142632" Dst="-1" /><file name="class-wp-filesystem-ftpsockets.php" server="shanegermann.com//montanameat/" local="3458210423" remote="318763443846142632" Dst="-1" /><file name="class-wp-filesystem-ssh2.php" server="shanegermann.com//montanameat/" local="3458210423" remote="318763443846142632" Dst="-1" /><file name="class-wp-importer.php" server="shanegermann.com//montanameat/" local="3458210423" remote="318763443846142632" Dst="-1" /><file name="class-wp-links-list-table.php" server="shanegermann.com//montanameat/" local="3458210423" remote="318763443846142632" Dst="-1" /><file name="class-wp-list-table.php" server="shanegermann.com//montanameat/" local="3458210424" remote="318763443846142632" Dst="-1" /><file name="class-wp-media-list-table.php" server="shanegermann.com//montanameat/" local="3458210424" remote="318763443846142632" Dst="-1" /><file name="class-wp-ms-sites-list-table.php" server="shanegermann.com//montanameat/" local="3458210424" remote="318763443846142632" Dst="-1" /><file name="class-wp-ms-themes-list-table.php" server="shanegermann.com//montanameat/" local="3458210424" remote="318763443846142632" Dst="-1" /><file name="class-wp-ms-users-list-table.php" server="shanegermann.com//montanameat/" local="3458210424" remote="318763443846142632" Dst="-1" /><file name="class-wp-plugin-install-list-table.php" server="shanegermann.com//montanameat/" local="3458210424" remote="318763443846142632" Dst="-1" /><file name="class-wp-plugins-list-table.php" server="shanegermann.com//montanameat/" local="3458210424" remote="318763443846142632" Dst="-1" /><file name="class-wp-terms-list-table.php" server="shanegermann.com//montanameat/" local="3458210424" remote="318763443846142632" Dst="-1" /><file name="class-wp-posts-list-table.php" server="shanegermann.com//montanameat/" local="3458210424" remote="318763443846142632" Dst="-1" /><file name="class-wp-theme-install-list-table.php" server="shanegermann.com//montanameat/" local="3458210425" remote="318763443846142632" Dst="-1" /><file name="class-wp-themes-list-table.php" server="shanegermann.com//montanameat/" local="3458210425" remote="318763443846142632" Dst="-1" /><file name="class-wp-upgrader.php" server="shanegermann.com//montanameat/" local="3458210425" remote="318763443846142632" Dst="-1" /><file name="class-wp-users-list-table.php" server="shanegermann.com//montanameat/" local="3458210425" remote="318763443846142632" Dst="-1" /><file name="comment.php" server="shanegermann.com//montanameat/" local="3458210425" remote="318763443846142632" Dst="-1" /><file name="continents-cities.php" server="shanegermann.com//montanameat/" local="3458210425" remote="318763443846142632" Dst="-1" /><file name="deprecated.php" server="shanegermann.com//montanameat/" local="3458210425" remote="318763443846142632" Dst="-1" /><file name="dashboard.php" server="shanegermann.com//montanameat/" local="3458210425" remote="318763443846142632" Dst="-1" /><file name="export.php" server="shanegermann.com//montanameat/" local="3458210425" remote="318763443846142632" Dst="-1" /><file name="file.php" server="shanegermann.com//montanameat/" local="3458210425" remote="318763443846142632" Dst="-1" /><file name="image.php" server="shanegermann.com//montanameat/" local="3458210426" remote="318763443846142632" Dst="-1" /><file name="image-edit.php" server="shanegermann.com//montanameat/" local="3458210426" remote="318763443846142632" Dst="-1" /><file name="import.php" server="shanegermann.com//montanameat/" local="3458210426" remote="318763443846142632" Dst="-1" /><file name="list-table.php" server="shanegermann.com//montanameat/" local="3458210426" remote="318763443846142632" Dst="-1" /><file name="menu.php" server="shanegermann.com//montanameat/" local="3458210426" remote="318763443846142632" Dst="-1" /><file name="media.php" server="shanegermann.com//montanameat/" local="3458210426" remote="318763443846142632" Dst="-1" /><file name="meta-boxes.php" server="shanegermann.com//montanameat/" local="3458210426" remote="318763443846142632" Dst="-1" /><file name="misc.php" server="shanegermann.com//montanameat/" local="3458210426" remote="318763443846142632" Dst="-1" /><file name="ms-deprecated.php" server="shanegermann.com//montanameat/" local="3458210426" remote="318763443846142632" Dst="-1" /><file name="ms.php" server="shanegermann.com//montanameat/" local="3458210427" remote="318763443846142632" Dst="-1" /><file name="nav-menu.php" server="shanegermann.com//montanameat/" local="3458210427" remote="318763443846142632" Dst="-1" /><file name="plugin-install.php" server="shanegermann.com//montanameat/" local="3458210427" remote="318763443846142632" Dst="-1" /><file name="plugin.php" server="shanegermann.com//montanameat/" local="3458210427" remote="318763443846142632" Dst="-1" /><file name="schema.php" server="shanegermann.com//montanameat/" local="3458210427" remote="318763443846142632" Dst="-1" /><file name="post.php" server="shanegermann.com//montanameat/" local="3458210427" remote="318763443846142632" Dst="-1" /><file name="screen.php" server="shanegermann.com//montanameat/" local="3458210427" remote="318763443846142632" Dst="-1" /><file name="taxonomy.php" server="shanegermann.com//montanameat/" local="3458210427" remote="318763443846142632" Dst="-1" /><file name="theme-install.php" server="shanegermann.com//montanameat/" local="3458210428" remote="318763443846142632" Dst="-1" /><file name="template.php" server="shanegermann.com//montanameat/" local="3458210428" remote="318763443846142632" Dst="-1" /><file name="theme.php" server="shanegermann.com//montanameat/" local="3458210428" remote="318763443846142632" Dst="-1" /><file name="update-core.php" server="shanegermann.com//montanameat/" local="3458210428" remote="318763443846142632" Dst="-1" /><file name="update.php" server="shanegermann.com//montanameat/" local="3458210428" remote="318763443846142632" Dst="-1" /><file name="user.php" server="shanegermann.com//montanameat/" local="3458210428" remote="318763443846142632" Dst="-1" /><file name="upgrade.php" server="shanegermann.com//montanameat/" local="3458210428" remote="318763443846142632" Dst="-1" /><file name="widgets.php" server="shanegermann.com//montanameat/" local="3458210428" remote="318763443846142632" Dst="-1" /></dwsync>